shtop/__init__.py
shtop/tui.py
shtop-0.0.3.data/scripts/shtop
shtop-0.0.3.dist-info/METADATA
shtop-0.0.3.dist-info/WHEEL
shtop-0.0.3.dist-info/top_level.txt
shtop-0.0.3.dist-info/RECORD
