Metadata-Version: 2.1
Name: shtop
Version: 0.0.3
Summary: Simple tui slurm job viewer.
Home-page: UNKNOWN
Author: Lukáš Plevač
Author-email: <lukas@plevac.eu>
License: UNKNOWN
Keywords: python,slurm,shtop,top,htop
Platform: UNKNOWN
Classifier: Development Status :: 3 - Alpha
Classifier: Intended Audience :: Education
Classifier: Programming Language :: Python :: 3
